telethon_secret_chat/__init__.py
telethon_secret_chat/secret_chat_manager.py
telethon_secret_chat/secret_methods.py
telethon_secret_chat/version.py
telethon_secret_chat/secret_sechma/__init__.py
telethon_secret_chat/secret_sechma/secretTL.py
telethon_secret_chat/storage/__init__.py
telethon_secret_chat/storage/abstract.py
telethon_secret_chat/storage/memory.py
telethon_secret_chat/storage/sqlite.py
telethon_secret_chat-0.2.4.dist-info/LICENSE
telethon_secret_chat-0.2.4.dist-info/METADATA
telethon_secret_chat-0.2.4.dist-info/WHEEL
telethon_secret_chat-0.2.4.dist-info/top_level.txt
telethon_secret_chat-0.2.4.dist-info/RECORD
