Metadata-Version: 2.1
Name: telethon-secret-chat
Version: 0.2.4
Summary: Telethon secret chat plugin
Home-page: https://github.com/painor/telethon-secret-chat
Author: painor
Author-email: topcode.softwares@gmail.com
License: MIT
Download-URL: https://github.com/painor/telethon-secret-chat/releases
Keywords: Telegram,Telethon,SecretChats,Plugin
Platform: UNKNOWN
Classifier: Development Status :: 3 - Alpha
Classifier: Intended Audience :: Developers
Classifier: Topic :: Communications :: Chat
Classifier: License :: OSI Approved :: MIT License
Classifier: Programming Language :: Python :: 3
Requires-Python: >=3.5
Requires-Dist: telethon
